[{"model": "players.player", "pk": 99377229, "fields": {"image": "player/Zion_SuperGirl_S4.png", "country": "SG", "status": "A", "dob": "1995-02-24", "position": ["Exp Laner"], "alternate_ids": "SuperGirl", "earning": 5282}}, {"model": "players.player", "pk": 64255404, "fields": {"image": "player/EVOS_SG_JPL_2.png", "country": "", "status": "A", "dob": "1995-12-23", "position": ["Roamer"], "alternate_ids": "", "earning": 47073}}, {"model": "players.player", "pk": 92314178, "fields": {"image": "", "country": "SG", "status": "A", "dob": null, "position": ["Exp Laner"], "alternate_ids": "Jae x love", "earning": 0}}, {"model": "players.player", "pk": 50362301, "fields": {"image": "player/EVOS_SG_Joxxx.png", "country": "SG", "status": "A", "dob": "2005-06-20", "position": ["Jungler"], "alternate_ids": "", "earning": 3785}}, {"model": "players.player", "pk": 79339532, "fields": {"image": "", "country": "SG", "status": "A", "dob": null, "position": ["Roamer"], "alternate_ids": "", "earning": 11998}}, {"model": "players.player", "pk": 52281994, "fields": {"image": "", "country": "SG", "status": "R", "dob": null, "position": ["Roamer", "Mid Laner"], "alternate_ids": "Ken", "earning": 7442}}, {"model": "players.player", "pk": 13591242, "fields": {"image": "", "country": "", "status": "", "dob": null, "position": [], "alternate_ids": "", "earning": 0}}, {"model": "players.player", "pk": 514399, "fields": {"image": "", "country": "SG", "status": "R", "dob": null, "position": ["Roamer", "Exp Laner"], "alternate_ids": "", "earning": 8119}}, {"model": "players.player", "pk": 45782527, "fields": {"image": "player/600px-RSG_Singapore_Lolsie.png", "country": "SG", "status": "A", "dob": null, "position": ["Roamer"], "alternate_ids": "", "earning": 9348}}]