[{"pk": 84825438, "fields": {"owner": 84825438, "facebook": "https://facebook.com/abamsaid2021"}}, {"pk": 2789507, "fields": {"owner": 2789507}}, {"pk": 55097853, "fields": {"owner": 55097853}}, {"pk": 7483364, "fields": {"owner": 7483364}}, {"pk": 26786235, "fields": {"owner": 26786235, "facebook": "https://facebook.com/fierafendiofficial"}}, {"pk": 54606382, "fields": {"owner": 54606382, "facebook": "https://facebook.com/theFatal5way"}}, {"pk": 97094632, "fields": {"owner": 97094632}}, {"pk": 32556402, "fields": {"owner": 32556402}}, {"pk": 12530475, "fields": {"owner": 12530475, "facebook": "https://facebook.com/HusKKieeCast"}}]