[{"pk": 54952722, "fields": {"player": 30816222, "team": 61240512, "date_joined": "2021-02-10", "date_left": "2021-08-19"}}, {"pk": 54040856, "fields": {"player": 30816222, "team": 10599349, "date_joined": "2021-08-19", "date_left": "2022-01-20"}}, {"pk": 71287807, "fields": {"player": 30816222, "team": 61240512, "date_joined": "2022-01-20", "date_left": "2022-03-17"}}, {"pk": 18233427, "fields": {"player": 30816222, "team": 10599349, "date_joined": "2022-03-17", "date_left": "2022-08-25"}}, {"pk": 40280199, "fields": {"player": 30816222, "team": 61240512, "date_joined": "2022-08-25", "date_left": null}}, {"pk": 11168378, "fields": {"player": 79886948, "team": 87080206, "date_joined": "2020-06-05", "date_left": "2021-02-14"}}, {"pk": 2480269, "fields": {"player": 79886948, "team": 92661639, "date_joined": "2020-11-10", "date_left": "2021-07-02"}}, {"pk": 13470685, "fields": {"player": 79886948, "team": 10352163, "date_joined": "2021-07-13", "date_left": "2022-05-20"}}, {"pk": 90185054, "fields": {"player": 79886948, "team": 10599349, "date_joined": "2022-08-16", "date_left": null}}, {"pk": 34386649, "fields": {"player": 78921142, "team": 61240512, "date_joined": "2022-01-20", "date_left": "2022-07-23"}}, {"pk": 38927965, "fields": {"player": 78921142, "team": 10599349, "date_joined": "2022-07-23", "date_left": null}}, {"pk": 12513955, "fields": {"player": 21725306, "team": 61240512, "date_joined": "2022-01-20", "date_left": "2022-07-30"}}, {"pk": 93411580, "fields": {"player": 21725306, "team": 10599349, "date_joined": "2022-07-30", "date_left": null}}, {"pk": 45747854, "fields": {"player": 46101640, "team": 10599349, "date_joined": "2022-07-29", "date_left": "2022-08-25"}}, {"pk": 55964800, "fields": {"player": 46101640, "team": 61240512, "date_joined": "2022-08-25", "date_left": null}}, {"pk": 82785376, "fields": {"player": 16671957, "team": 47682518, "date_joined": "2021-02-12", "date_left": "2022-01-12"}}, {"pk": 24453558, "fields": {"player": 16671957, "team": 4344756, "date_joined": "2022-01-12", "date_left": null}}, {"pk": 75529105, "fields": {"player": 96705342, "team": 45585623, "date_joined": "2019-01-31", "date_left": "2020-01-27"}}, {"pk": 17092448, "fields": {"player": 96705342, "team": 4344756, "date_joined": "2021-08-27", "date_left": "2022-07-22"}}, {"pk": 1379798, "fields": {"player": 96705342, "team": 4344756, "date_joined": "2022-03-05", "date_left": "2022-07-22"}}, {"pk": 82137078, "fields": {"player": 96705342, "team": 4344756, "date_joined": "2022-07-22", "date_left": "2022-08-11", "status": "Inactive"}}, {"pk": 64403532, "fields": {"player": 13227054, "team": 37710037, "date_joined": "2018-06-01", "date_left": "2019-07-23"}}, {"pk": 20989243, "fields": {"player": 13227054, "team": 79247991, "date_joined": "2019-07-23", "date_left": "2021-07-23"}}, {"pk": 8792727, "fields": {"player": 13227054, "team": 4344756, "date_joined": "2021-09-10", "date_left": "2022-07-22"}}, {"pk": 40159858, "fields": {"player": 13227054, "team": 4344756, "date_joined": "2022-07-22", "date_left": null, "status": "Inactive"}}, {"pk": 45727252, "fields": {"player": 5080269, "team": 79247991, "date_joined": "2020-02-01", "date_left": "2021-07-23"}}, {"pk": 90507831, "fields": {"player": 5080269, "team": 4344756, "date_joined": "2021-09-10", "date_left": null}}, {"pk": 27535502, "fields": {"player": 73126181, "team": 17298429, "date_joined": "2017-10-02", "date_left": "2018-04-05"}}, {"pk": 78049993, "fields": {"player": 73126181, "team": 79247991, "date_joined": "2018-04-23", "date_left": "2018-08-10"}}, {"pk": 18545782, "fields": {"player": 73126181, "team": 45585623, "date_joined": "2018-08-10", "date_left": "2019-02-18"}}, {"pk": 8838341, "fields": {"player": 73126181, "team": 37710037, "date_joined": "2019-01-12", "date_left": "2019-07-23"}}, {"pk": 11470492, "fields": {"player": 73126181, "team": 79247991, "date_joined": "2019-07-23", "date_left": "2020-02-13"}}, {"pk": 71643303, "fields": {"player": 73126181, "team": 79275682, "date_joined": "2020-02-13", "date_left": "2020-02-27"}}, {"pk": 66689239, "fields": {"player": 73126181, "team": 79247991, "date_joined": "2020-02-27", "date_left": "2021-07-23"}}, {"pk": 20696624, "fields": {"player": 73126181, "team": 4344756, "date_joined": "2021-09-10", "date_left": null}}, {"pk": 83576239, "fields": {"player": 23423125, "team": 74104696, "date_joined": "2021-09-19", "date_left": null}}]